{
    "title": "If opposites attract, why is my sister so pretty?",
    "date": "March 21, 2013",
    "links": [
        "http://en.wikipedia.org/wiki/Asexual_reproduction#Alternation_between_sexual_and_asexual_reproduction",
        "http://en.wikipedia.org/wiki/Hybrid_vigor",
        "http://en.wikipedia.org/wiki/Genetic_sexual_attraction",
        "http://squid314.livejournal.com/331632.html",
        "http://phys.org/news199509031.html",
        "https://www.scienceupdate.com/2005/09/similarities-attract/",
        "http://en.wikipedia.org/wiki/Westermarck_effect"
    ],
    "url": "https://slatestarcodex.com/2013/03/21/if-opposites-attract-why-is-my-sister-so-pretty/",
    "summary": "Key ideas:\n- Organisms often alternate between sexual and asexual reproduction to ensure their genes survive the competition.\n- Mating with organisms genetically different from oneself can increase offspring success and confound parasites.\n- Major histocompatibility complex (MHC) genes play a role in immune system diversity, and animals may choose mates with different MHCs for optimal offspring health.\n- Humans are attracted to those genetically similar to them except in the case of MHCs. \n\nKey learnings:\n- Offspring success often depends on genetic diversity, but the reasons for mate choice are not fully understood.\n- The major histocompatibility complex may play a role in human mate choice.\n- Close relatives separated at birth often experience strong sexual attraction upon reunion, even to opposite-sex parents. \n\nKey questions:\n- How do organisms balance competition with genetic diversity in reproduction?\n- What other factors besides MHC genes may contribute to optimal offspring health?\n- What is the explanation for humans being attracted to individuals genetically similar to them, except in the case of MHCs?"
}