{
    "title": "Not Even A Real Links Post, Just A Blatant Ad",
    "date": "May 6, 2014",
    "links": [
        "http://svgives.razoo.com/giving_events/svg14/home",
        "http://intelligence.org/",
        "http://svgives.razoo.com/story/Machine-Intelligence-Research-Institute"
    ],
    "url": "https://slatestarcodex.com/2014/05/06/not-even-a-real-links-post-just-a-blatant-ad/",
    "summary": "Key ideas:\n- There is a charity event going on where whoever gets the most unique donors of $10 or more wins a prize supposedly valued at $250,000.\n- MIRI is a group that works on ensuring a positive singularity and friendly AI. \n- MIRI is currently close to winning the top place in the charity event.\n\nKey learnings:\n- Donating to MIRI can help support their work on ensuring a positive singularity and friendly AI.\n\nKey questions:\n- Should I consider donating to MIRI to help support their work?"
}