{
    "title": "The Phatic And The Anti-Inductive",
    "date": "January 11, 2015",
    "links": [
        "https://slatestarcodex.com/2014/12/07/a-story-with-zombies/"
    ],
    "url": "https://slatestarcodex.com/2015/01/11/the-phatic-and-the-anti-inductive/",
    "summary": "Key ideas:\n- Phatic communication refers to talking for the sake of talking to acknowledge acquaintances and maintain social relationships\n- Anti-inductive institutions or systems are those that become more complex and difficult to exploit when patterns are discovered, such as the stock market and job-seeking\n- Supportive therapy can be phatic or anti-inductive depending on the patient and therapist's communication preferences\n- Appreciating the phatic can be beneficial for maintaining social relationships and acknowledging gratitude\n\nKey learnings:\n- Phatic communication and anti-inductive institutions are important concepts to consider when understanding various systems and interactions\n- Therapy can be improved by recognizing when to use phatic or anti-inductive communication based on the patient's needs and preferences\n- Appreciating the importance of phatic communication can help maintain social relationships and show gratitude\n\nKey questions:\n- How can individuals identify whether they or others prefer phatic or anti-inductive communication?\n- Are there any other examples of anti-inductive systems or institutions besides the stock market?\n- How can therapists determine whether to utilize phatic or anti-inductive approaches during supportive therapy sessions?"
}