{
    "title": "2016 Predictions: Calibration Results",
    "date": "December 31, 2016",
    "links": [
        "https://slatestarcodex.com/2015/01/01/2014-predictions-calibration-results/",
        "https://slatestarcodex.com/2016/01/02/2015-predictions-calibration-results/",
        "https://slatestarcodex.com/2015/01/01/2014-predictions-calibration-results/",
        "https://slatestarcodex.com/2016/01/02/2015-predictions-calibration-results/"
    ],
    "url": "https://slatestarcodex.com/2016/12/31/2016-predictions-calibration-results/",
    "summary": "Key ideas:\n- The author made predictions for various events in 2016\n- Predictions covered world events, personal and community matters\n- The author assigned probabilities to each of the predictions\n\nKey learnings:\n- The author's predictions had an overall accuracy of 77%\n- The author was relatively underconfident in predictions with a 70% probability\n- The author's predictions had a high accuracy for 95% and 99% probabilities\n\nKey questions:\n- What were the author's predictions for 2017?\n- Did the author make any notable changes to their predicting strategy after evaluating the accuracy of their 2016 predictions?\n- How do the author's predictions reflect their general outlook on world events and personal matters?"
}