{
    "title": "Partial Credit",
    "date": "August 21, 2017",
    "links": [],
    "url": "https://slatestarcodex.com/2017/08/21/partial-credit/",
    "summary": "Key ideas\n- Explorer claims to possess great magic and bluffing to have the power to blot out the sun to escape from the savages.\n- The savages refuse to believe the explorer's claims and instead offer to eat him as originally planned.\n- The explorer attempts to use a pinhole projector made of bark to convince the savages of his ability to blot out the sun.\n- The savages remain skeptical and eventually allow the explorer to leave when they can't confirm that the sun is indeed blotted out.\n\nKey learnings\n- Bluffing can work initially but ultimately, providing proof is necessary to convince skeptics.\n- Optics and science are not understood by everyone, and language barriers may further complicate explanations.\n- Sometimes what seems like a good idea can turn into a disaster.\n\nKey questions\n- Can bluffing work in other situations besides convincing skeptics of a magic trick?\n- How much scientific concepts and language does one need to know before attempting to explain something to someone else?\n- What other instances demonstrate the difficulty of communicating across language and cultural barriers?"
}