{
    "title": "OT100: One Hunthread",
    "date": "April 22, 2018",
    "links": [
        "https://www.reddit.com/r/slatestarcodex/",
        "https://discord.gg/gpaTCxh",
        "https://www.patreon.com/berkeleyreach/overview",
        "https://www.lesswrong.com/community",
        "https://www.reddit.com/r/slatestarcodex/comments/8bypq0/reading_notes_civilization_capitalism_15th18th/"
    ],
    "url": "https://slatestarcodex.com/2018/04/22/ot100-one-hunthread/",
    "summary": "Key ideas:\n- This is a weekly open thread where anyone can post about anything they want or ask random questions.\n- The author encourages readers to donate to the Bay Area rationality community center's Patreon.\n- Less Wrong has a high-tech meetup page that helps readers find SSC meetups near them.\n\nKey learnings:\n- The Bay Area rationality community center still needs more donations to function properly.\n- The Less Wrong high-tech meetup page has an option to limit meetups to SSC only.\n- The author plans to transfer the meetup tab of the blog to the Less Wrong high-tech meetup page.\n\nKey questions:\n- None mentioned in this portion of the blog post."
}